{"title":"about","type":"page","uid":"03933793d01427bd4ef056d0a9b02560","text":"谨以此献给我GitHub Pages + Hexo(theme:Aurora)2025.06.01-? ","date":"2025-06-01T12:06:03.000Z","updated":"2025-06-02T06:25:40.092Z","comments":true,"path":"api/pages/about/index.json","covers":null,"excerpt":"","content":"<h1 id=\"谨以此献给我\"><a href=\"#谨以此献给我\" class=\"headerlink\" title=\"谨以此献给我\"></a>谨以此献给我</h1><p>GitHub Pages + Hexo(theme:Aurora)<br>2025.06.01-?</p>\n","count_time":{"symbolsCount":52,"symbolsTime":"1 mins."},"toc":"<ol class=\"toc\"><li class=\"toc-item toc-level-1\"><a class=\"toc-link\" href=\"#%E8%B0%A8%E4%BB%A5%E6%AD%A4%E7%8C%AE%E7%BB%99%E6%88%91\"><span class=\"toc-text\">谨以此献给我</span></a></li></ol>","data":[]}